agentopera/__about__.py
agentopera/__init__.py
agentopera/agents/__init__.py
agentopera/agents/py.typed
agentopera/agents/agents/__init__.py
agentopera/agents/agents/file_surfer/__init__.py
agentopera/agents/agents/file_surfer/_file_surfer.py
agentopera/agents/agents/file_surfer/_markdown_file_browser.py
agentopera/agents/agents/file_surfer/_tool_definitions.py
agentopera/agents/agents/magentic_one/__init__.py
agentopera/agents/agents/magentic_one/_magentic_one_coder_agent.py
agentopera/agents/agents/openai/__init__.py
agentopera/agents/agents/openai/_openai_assistant_agent.py
agentopera/agents/agents/video_surfer/__init__.py
agentopera/agents/agents/video_surfer/_video_surfer.py
agentopera/agents/agents/video_surfer/tools.py
agentopera/agents/agents/web_surfer/__init__.py
agentopera/agents/agents/web_surfer/_events.py
agentopera/agents/agents/web_surfer/_multimodal_web_surfer.py
agentopera/agents/agents/web_surfer/_prompts.py
agentopera/agents/agents/web_surfer/_set_of_mark.py
agentopera/agents/agents/web_surfer/_tool_definitions.py
agentopera/agents/agents/web_surfer/_types.py
agentopera/agents/agents/web_surfer/page_script.js
agentopera/agents/agents/web_surfer/playwright_controller.py
agentopera/agents/auth/azure/__init__.py
agentopera/agents/cache_store/__init__.py
agentopera/agents/cache_store/diskcache.py
agentopera/agents/cache_store/redis.py
agentopera/agents/code_executors/_common.py
agentopera/agents/code_executors/azure/__init__.py
agentopera/agents/code_executors/azure/_azure_container_code_executor.py
agentopera/agents/code_executors/docker/__init__.py
agentopera/agents/code_executors/docker/_docker_code_executor.py
agentopera/agents/code_executors/jupyter/__init__.py
agentopera/agents/code_executors/jupyter/_jupyter_code_executor.py
agentopera/agents/code_executors/local/__init__.py
agentopera/agents/experimental/__init__.py
agentopera/agents/experimental/task_centric_memory/README.md
agentopera/agents/experimental/task_centric_memory/__init__.py
agentopera-0.0.8.dist-info/METADATA
agentopera-0.0.8.dist-info/WHEEL
agentopera-0.0.8.dist-info/licenses/LICENSE
agentopera-0.0.8.dist-info/licenses/LICENSE.txt
agentopera-0.0.8.dist-info/RECORD
