Metadata-Version: 2.4
Name: agentopera
Version: 0.0.8
Project-URL: Documentation, https://github.com/chaoyanghe/agentopera#readme
Project-URL: Issues, https://github.com/chaoyanghe/agentopera/issues
Project-URL: Source, https://github.com/chaoyanghe/agentopera
Author-email: chaoyanghe <choayanghe.com@gmail.com>
License-Expression: MIT
License-File: LICENSE
License-File: LICENSE.txt
Classifier: Development Status :: 4 - Beta
Classifier: Programming Language :: Python
Classifier: Programming Language :: Python :: 3.8
Classifier: Programming Language :: Python :: 3.9
Classifier: Programming Language :: Python :: 3.10
Classifier: Programming Language :: Python :: 3.11
Classifier: Programming Language :: Python :: 3.12
Classifier: Programming Language :: Python :: Implementation :: CPython
Classifier: Programming Language :: Python :: Implementation :: PyPy
Requires-Python: >=3.8
Requires-Dist: chainlit
Requires-Dist: cookiecutter
Requires-Dist: grpcio-tools~=1.70.0
Requires-Dist: mypy-protobuf
Requires-Dist: mypy==1.13.0
Requires-Dist: packaging
Requires-Dist: poethepoet
Requires-Dist: polars
Requires-Dist: pyright==1.1.389
Requires-Dist: pytest
Requires-Dist: pytest-asyncio
Requires-Dist: pytest-cov
Requires-Dist: pytest-mock
Requires-Dist: pytest-xdist
Requires-Dist: rich
Requires-Dist: ruff==0.4.8
Requires-Dist: streamlit
Requires-Dist: tomli
Requires-Dist: tomli-w
Requires-Dist: typer
